grid/__init__.py
grid/repl.py
grid/sdk/__init__.py
grid/sdk/resource_manager.py
grid/sdk/session_manager.py
grid/sdk/commander/client.py
grid/sdk/commander/core.py
grid/sdk/commander/security.py
grid/sdk/commander/server.py
grid/utils/airgen_utils.py
grid/utils/auth_utils.py
grid/utils/azcopy_downloader.py
grid/utils/config_handler.py
grid/utils/constants.py
grid/utils/docker-compose.yml
grid/utils/grid_asset_downloader.py
grid/utils/health_server.py
grid/utils/isaac_utils.py
grid/utils/network_utils.py
grid/utils/repl_helpers.py
grid/utils/storage_utils.py
grid_enterprise-0.1.4.dist-info/METADATA
grid_enterprise-0.1.4.dist-info/WHEEL
grid_enterprise-0.1.4.dist-info/entry_points.txt
grid_enterprise-0.1.4.dist-info/RECORD
