Metadata-Version: 2.4
Name: grid-enterprise
Version: 0.1.4
Summary: General Robot Intelligence Development Platform - Enterprise Console
Project-URL: Homepage, https://generalrobotics.company
Author-email: General Robotics <info@generalrobotics.company>
Classifier: Operating System :: OS Independent
Classifier: Programming Language :: Python :: 3
Requires-Python: >=3.11
Requires-Dist: art
Requires-Dist: docker
Requires-Dist: fastapi
Requires-Dist: httpx
Requires-Dist: packaging
Requires-Dist: paramiko
Requires-Dist: pyjwt
Requires-Dist: pyyaml
Requires-Dist: rich
Requires-Dist: tabulate
Requires-Dist: uvicorn
